fake_coro/__init__.py
fake_coro/py.typed
fake_coro-0.1.1.dist-info/LICENSE
fake_coro-0.1.1.dist-info/METADATA
fake_coro-0.1.1.dist-info/WHEEL
fake_coro-0.1.1.dist-info/RECORD
