Metadata-Version: 2.1
Name: fake-coro
Version: 0.1.1
Summary: Coroutines emulated with threads.
Home-page: https://github.com/NKID00/fake-coro
License: MIT
Author: NKID00
Author-email: this@nkid00.name
Requires-Python: >=3.7,<4.0
Classifier: License :: OSI Approved :: MIT License
Classifier: Programming Language :: Python :: 3
Classifier: Programming Language :: Python :: 3.7
Classifier: Programming Language :: Python :: 3.8
Classifier: Programming Language :: Python :: 3.9
Classifier: Programming Language :: Python :: 3.10
Classifier: Programming Language :: Python :: 3.11
Project-URL: Repository, https://github.com/NKID00/fake-coro
